{
    "list": [
      {
        "id": 1,
        "thumbnail": "https://picsum.photos/400",
        "title": "소모임 어플",
        "start_date": "2019.10",
        "end_date": "2019.12",
        "skill": ["Xml", "java", "Xml", "php", "android-studio", "MySql"],
        "category": "Academic",
        "description": "대학교 학생들의 학업 증진과 커뮤니티 활성화를 목표로한 소모임 중개 서비스",
        "link": {
            "git": "",
            "url": ""
        }
      },
      {
        "id": 2,
        "thumbnail": "https://picsum.photos/400",
        "title": "블록체인 중고거래 어플",
        "start_date": "2020.02",
        "end_date": "2020.07",
        "skill": ["Xml", "java", "android-studio", "ethereum blockchain", "MySql"],
        "category": "Academic",
        "description": "블록체인을 활용한 중고 전자기기 거래 어플리케이션.",
        "link": {
            "git": "",
            "url": ""
        }
      },
      {
        "id": 3,
        "thumbnail": "https://picsum.photos/400",
        "title": "ATUM",
        "start_date": "2020.06",
        "end_date": "2022.12",
        "skill": ["java", "spring boot", "mariaDB", "angularjs", "javascript", "html", "css", "jquery"],
        "category": "Professional",
        "description": "- Low Code Development Plateform, 개발화면(ux생성화면/Query생성화면/DB table 생성 화면) + 프로젝트관리화면(일정, 담당자, 진행상황 관리화면/데이터 모델링 화면) 으로 구성",
        "link": {
            "git": "",
            "url": ""
        }
      },
      {
        "id": 4,
        "thumbnail": "https://picsum.photos/400",
        "title": "CANAPE",
        "start_date": "2023.02",
        "skill": ["java", "spring boot", "mariaDB", "vue.js", "javascript", "html", "css"],
        "category": "Professional",
        "description": "파일관리 화면/UI디자인 화면/Event 설정화면으로 이루어진 목업툴",
        "link": {
            "git": "",
            "url": ""
        }
      }
    ]
  }